{
  "versionCode": 8,
  "versionName": "2.8.5",
  "updateTime": "2025-12-30",
  "forceUpdate": false,
  "msg": "NyaLoader v2.8.5 功能增强与兼容性更新！\n\n修复了对于主页异常展开\n修复了对于字体缩进的问题\n更新依赖库最新版本",
  "apkUrls": {
    "universal": "https://github.com/Jinsens/NyaLoader/releases/download/v2.8.5/app-universal-release.apk",
    "arm64-v8a": "https://github.com/Jinsens/NyaLoader/releases/download/v2.8.5/app-arm64-v8a-release.apk",
    "armeabi-v7a": "https://github.com/Jinsens/NyaLoader/releases/download/v2.8.5/app-armeabi-v7a-release.apk",
    "x86": "https://github.com/Jinsens/NyaLoader/releases/download/v2.8.5/app-x86-release.apk",
    "x86_64": "https://github.com/Jinsens/NyaLoader/releases/download/v2.8.5/app-x86_64-release.apk"
  }
}
